{"type": "FeatureCollection", "features": [{"type": "Feature", "geometry": {"type": "Point", "coordinates": [0.274559, -0.000977]}, "properties": {}}, {"type": "Feature", "geometry": {"type": "Point", "coordinates": [0.212761, -0.000977]}, "properties": {}}, {"type": "Feature", "geometry": {"type": "Point", "coordinates": [0.160507, -0.000977]}, "properties": {}}, {"type": "Feature", "geometry": {"type": "Point", "coordinates": [0.148277, -0.000977]}, "properties": {}}, {"type": "Feature", "geometry": {"type": "Point", "coordinates": [0.120148, -0.000977]}, "properties": {}}, {"type": "Feature", "geometry": {"type": "Point", "coordinates": [0.18187, -0.000977]}, "properties": {}}, {"type": "Feature", "geometry": {"type": "Point", "coordinates": [0.258118, -0.000977]}, "properties": {}}, {"type": "Feature", "geometry": {"type": "Point", "coordinates": [0.279739, -0.000977]}, "properties": {}}, {"type": "Feature", "geometry": {"type": "Point", "coordinates": [0.296356, -0.000977]}, "properties": {}}, {"type": "Feature", "geometry": {"type": "Point", "coordinates": [0.295845, -0.000977]}, "properties": {}}, {"type": "Feature", "geometry": {"type": "Point", "coordinates": [0.282021, -0.029762]}, "properties": {}}, {"type": "Feature", "geometry": {"type": "Point", "coordinates": [0.221779, -0.02977]}, "properties": {}}, {"type": "Feature", "geometry": {"type": "Point", "coordinates": [0.170479, -0.029778]}, "properties": {}}, {"type": "Feature", "geometry": {"type": "Point", "coordinates": [0.243576, -0.029785]}, "properties": {}}, {"type": "Feature", "geometry": {"type": "Point", "coordinates": [0.280762, -0.029793]}, "properties": {}}, {"type": "Feature", "geometry": {"type": "Point", "coordinates": [0.307747, -0.000977]}, "properties": {}}, {"type": "Feature", "geometry": {"type": "Point", "coordinates": [0.339935, -0.000977]}, "properties": {}}, {"type": "Feature", "geometry": {"type": "Point", "coordinates": [0.318146, -0.000977]}, "properties": {}}, {"type": "Feature", "geometry": {"type": "Point", "coordinates": [0.378456, -0.000977]}, "properties": {}}, {"type": "Feature", "geometry": {"type": "Point", "coordinates": [0.379944, -0.000977]}, "properties": {}}, {"type": "Feature", "geometry": {"type": "Point", "coordinates": [0.42366, -0.000977]}, "properties": {}}, {"type": "Feature", "geometry": {"type": "Point", "coordinates": [0.442917, -0.000977]}, "properties": {}}, {"type": "Feature", "geometry": {"type": "Point", "coordinates": [0.46563, -0.000977]}, "properties": {}}, {"type": "Feature", "geometry": {"type": "Point", "coordinates": [0.469643, -0.000977]}, "properties": {}}, {"type": "Feature", "geometry": {"type": "Point", "coordinates": [0.371048, -0.000977]}, "properties": {}}, {"type": "Feature", "geometry": {"type": "Point", "coordinates": [0.397583, -0.030411]}, "properties": {}}, {"type": "Feature", "geometry": {"type": "Point", "coordinates": [0.419395, -0.030418]}, "properties": {}}, {"type": "Feature", "geometry": {"type": "Point", "coordinates": [0.356125, -0.030426]}, "properties": {}}, {"type": "Feature", "geometry": {"type": "Point", "coordinates": [0.398193, -0.030434]}, "properties": {}}, {"type": "Feature", "geometry": {"type": "Point", "coordinates": [0.47963, -0.030441]}, "properties": {}}, {"type": "Feature", "geometry": {"type": "Point", "coordinates": [-0.068726, -0.000977]}, "properties": {}}, {"type": "Feature", "geometry": {"type": "Point", "coordinates": [-0.114594, -0.000977]}, "properties": {}}, {"type": "Feature", "geometry": {"type": "Point", "coordinates": [-0.048409, -0.000977]}, "properties": {}}, {"type": "Feature", "geometry": {"type": "Point", "coordinates": [0.017265, -0.000977]}, "properties": {}}, {"type": "Feature", "geometry": {"type": "Point", "coordinates": [0.092308, -0.000977]}, "properties": {}}, {"type": "Feature", "geometry": {"type": "Point", "coordinates": [0.042488, -0.000977]}, "properties": {}}, {"type": "Feature", "geometry": {"type": "Point", "coordinates": [0.071243, -0.000977]}, "properties": {}}, {"type": "Feature", "geometry": {"type": "Point", "coordinates": [0.12822, -0.000977]}, "properties": {}}, {"type": "Feature", "geometry": {"type": "Point", "coordinates": [0.149902, -0.000977]}, "properties": {}}, {"type": "Feature", "geometry": {"type": "Point", "coordinates": [0.099892, -0.000977]}, "properties": {}}, {"type": "Feature", "geometry": {"type": "Point", "coordinates": [0.001999, -0.03022]}, "properties": {}}, {"type": "Feature", "geometry": {"type": "Point", "coordinates": [0.152679, -0.030228]}, "properties": {}}, {"type": "Feature", "geometry": {"type": "Point", "coordinates": [0.082535, -0.030235]}, "properties": {}}, {"type": "Feature", "geometry": {"type": "Point", "coordinates": [0.14119, -0.030243]}, "properties": {}}, {"type": "Feature", "geometry": {"type": "Point", "coordinates": [-0.046379, -0.030251]}, "properties": {}}, {"type": "Feature", "geometry": {"type": "Point", "coordinates": [-0.073479, -0.000977]}, "properties": {}}, {"type": "Feature", "geometry": {"type": "Point", "coordinates": [-0.147423, -0.000977]}, "properties": {}}, {"type": "Feature", "geometry": {"type": "Point", "coordinates": [-0.205421, -0.000977]}, "properties": {}}, {"type": "Feature", "geometry": {"type": "Point", "coordinates": [-0.266685, -0.000977]}, "properties": {}}, {"type": "Feature", "geometry": {"type": "Point", "coordinates": [-0.268265, -0.000977]}, "properties": {}}, {"type": "Feature", "geometry": {"type": "Point", "coordinates": [-0.196732, -0.000977]}, "properties": {}}, {"type": "Feature", "geometry": {"type": "Point", "coordinates": [-0.13459, -0.000977]}, "properties": {}}, {"type": "Feature", "geometry": {"type": "Point", "coordinates": [-0.151314, -0.000977]}, "properties": {}}, {"type": "Feature", "geometry": {"type": "Point", "coordinates": [-0.05809, -0.000977]}, "properties": {}}, {"type": "Feature", "geometry": {"type": "Point", "coordinates": [0.023949, -0.000977]}, "properties": {}}, {"type": "Feature", "geometry": {"type": "Point", "coordinates": [0.025215, -0.029953]}, "properties": {}}, {"type": "Feature", "geometry": {"type": "Point", "coordinates": [0.022408, -0.029961]}, "properties": {}}, {"type": "Feature", "geometry": {"type": "Point", "coordinates": [-0.247253, -0.029968]}, "properties": {}}, {"type": "Feature", "geometry": {"type": "Point", "coordinates": [0.038185, -0.029976]}, "properties": {}}, {"type": "Feature", "geometry": {"type": "Point", "coordinates": [-0.0373, -0.029984]}, "properties": {}}, {"type": "Feature", "geometry": {"type": "Point", "coordinates": [-0.018494, -0.000977]}, "properties": {}}, {"type": "Feature", "geometry": {"type": "Point", "coordinates": [-0.072517, -0.000977]}, "properties": {}}, {"type": "Feature", "geometry": {"type": "Point", "coordinates": [-0.106262, -0.000977]}, "properties": {}}, {"type": "Feature", "geometry": {"type": "Point", "coordinates": [-0.100876, -0.000977]}, "properties": {}}, {"type": "Feature", "geometry": {"type": "Point", "coordinates": [-0.041115, -0.000977]}, "properties": {}}, {"type": "Feature", "geometry": {"type": "Point", "coordinates": [0.030502, -0.000977]}, "properties": {}}, {"type": "Feature", "geometry": {"type": "Point", "coordinates": [0.092049, -0.000977]}, "properties": {}}, {"type": "Feature", "geometry": {"type": "Point", "coordinates": [0.106499, -0.000977]}, "properties": {}}, {"type": "Feature", "geometry": {"type": "Point", "coordinates": [-0.071556, -0.000977]}, "properties": {}}, {"type": "Feature", "geometry": {"type": "Point", "coordinates": [0.061653, -0.000977]}, "properties": {}}, {"type": "Feature", "geometry": {"type": "Point", "coordinates": [-0.005424, -0.029915]}, "properties": {}}, {"type": "Feature", "geometry": {"type": "Point", "coordinates": [-0.012459, -0.029922]}, "properties": {}}, {"type": "Feature", "geometry": {"type": "Point", "coordinates": [-0.108086, -0.02993]}, "properties": {}}, {"type": "Feature", "geometry": {"type": "Point", "coordinates": [-0.11348, -0.029938]}, "properties": {}}, {"type": "Feature", "geometry": {"type": "Point", "coordinates": [0.05603, -0.029945]}, "properties": {}}, {"type": "Feature", "geometry": {"type": "Point", "coordinates": [-0.22567, -0.000977]}, "properties": {}}, {"type": "Feature", "geometry": {"type": "Point", "coordinates": [-0.156334, -0.000977]}, "properties": {}}, {"type": "Feature", "geometry": {"type": "Point", "coordinates": [-0.143806, -0.000977]}, "properties": {}}, {"type": "Feature", "geometry": {"type": "Point", "coordinates": [-0.282265, -0.000977]}, "properties": {}}, {"type": "Feature", "geometry": {"type": "Point", "coordinates": [-0.213234, -0.000977]}, "properties": {}}, {"type": "Feature", "geometry": {"type": "Point", "coordinates": [-0.151268, -0.000977]}, "properties": {}}, {"type": "Feature", "geometry": {"type": "Point", "coordinates": [-0.170975, -0.000977]}, "properties": {}}, {"type": "Feature", "geometry": {"type": "Point", "coordinates": [-0.245247, -0.000977]}, "properties": {}}, {"type": "Feature", "geometry": {"type": "Point", "coordinates": [-0.295464, -0.000977]}, "properties": {}}, {"type": "Feature", "geometry": {"type": "Point", "coordinates": [-0.223259, -0.000977]}, "properties": {}}, {"type": "Feature", "geometry": {"type": "Point", "coordinates": [-0.256401, -0.030258]}, "properties": {}}, {"type": "Feature", "geometry": {"type": "Point", "coordinates": [-0.20134, -0.030266]}, "properties": {}}, {"type": "Feature", "geometry": {"type": "Point", "coordinates": [-0.130196, -0.030273]}, "properties": {}}, {"type": "Feature", "geometry": {"type": "Point", "coordinates": [-0.142296, -0.030281]}, "properties": {}}, {"type": "Feature", "geometry": {"type": "Point", "coordinates": [-0.256744, -0.030289]}, "properties": {}}, {"type": "Feature", "geometry": {"type": "Point", "coordinates": [0.462463, -0.000977]}, "properties": {}}, {"type": "Feature", "geometry": {"type": "Point", "coordinates": [0.468048, -0.000977]}, "properties": {}}, {"type": "Feature", "geometry": {"type": "Point", "coordinates": [0.426811, -0.000977]}, "properties": {}}, {"type": "Feature", "geometry": {"type": "Point", "coordinates": [0.383636, -0.000977]}, "properties": {}}, {"type": "Feature", "geometry": {"type": "Point", "coordinates": [0.339493, -0.000977]}, "properties": {}}, {"type": "Feature", "geometry": {"type": "Point", "coordinates": [0.397141, -0.000977]}, "properties": {}}, {"type": "Feature", "geometry": {"type": "Point", "coordinates": [0.350586, -0.000977]}, "properties": {}}, {"type": "Feature", "geometry": {"type": "Point", "coordinates": [0.388756, -0.000977]}, "properties": {}}, {"type": "Feature", "geometry": {"type": "Point", "coordinates": [0.424995, -0.000977]}, "properties": {}}, {"type": "Feature", "geometry": {"type": "Point", "coordinates": [0.474701, -0.000977]}, "properties": {}}, {"type": "Feature", "geometry": {"type": "Point", "coordinates": [0.464951, -0.030373]}, "properties": {}}, {"type": "Feature", "geometry": {"type": "Point", "coordinates": [0.377678, -0.03038]}, "properties": {}}, {"type": "Feature", "geometry": {"type": "Point", "coordinates": [0.474426, -0.030388]}, "properties": {}}, {"type": "Feature", "geometry": {"type": "Point", "coordinates": [0.485306, -0.030396]}, "properties": {}}, {"type": "Feature", "geometry": {"type": "Point", "coordinates": [0.442535, -0.030403]}, "properties": {}}, {"type": "Feature", "geometry": {"type": "Point", "coordinates": [0.258827, -0.000977]}, "properties": {}}, {"type": "Feature", "geometry": {"type": "Point", "coordinates": [0.18293, -0.000977]}, "properties": {}}, {"type": "Feature", "geometry": {"type": "Point", "coordinates": [0.096138, -0.000977]}, "properties": {}}, {"type": "Feature", "geometry": {"type": "Point", "coordinates": [0.127182, -0.000977]}, "properties": {}}, {"type": "Feature", "geometry": {"type": "Point", "coordinates": [0.138336, -0.000977]}, "properties": {}}, {"type": "Feature", "geometry": {"type": "Point", "coordinates": [0.126038, -0.000977]}, "properties": {}}, {"type": "Feature", "geometry": {"type": "Point", "coordinates": [0.180305, -0.000977]}, "properties": {}}, {"type": "Feature", "geometry": {"type": "Point", "coordinates": [0.239906, -0.000977]}, "properties": {}}, {"type": "Feature", "geometry": {"type": "Point", "coordinates": [0.209435, -0.000977]}, "properties": {}}, {"type": "Feature", "geometry": {"type": "Point", "coordinates": [0.212364, -0.000977]}, "properties": {}}, {"type": "Feature", "geometry": {"type": "Point", "coordinates": [0.232071, -0.029839]}, "properties": {}}, {"type": "Feature", "geometry": {"type": "Point", "coordinates": [0.227737, -0.029846]}, "properties": {}}, {"type": "Feature", "geometry": {"type": "Point", "coordinates": [0.101128, -0.029854]}, "properties": {}}, {"type": "Feature", "geometry": {"type": "Point", "coordinates": [0.157768, -0.029861]}, "properties": {}}, {"type": "Feature", "geometry": {"type": "Point", "coordinates": [0.104118, -0.029869]}, "properties": {}}, {"type": "Feature", "geometry": {"type": "Point", "coordinates": [-0.383102, -0.000977]}, "properties": {}}, {"type": "Feature", "geometry": {"type": "Point", "coordinates": [-0.404701, -0.000977]}, "properties": {}}, {"type": "Feature", "geometry": {"type": "Point", "coordinates": [-0.354019, -0.000977]}, "properties": {}}, {"type": "Feature", "geometry": {"type": "Point", "coordinates": [-0.359688, -0.000977]}, "properties": {}}, {"type": "Feature", "geometry": {"type": "Point", "coordinates": [-0.422707, -0.000977]}, "properties": {}}, {"type": "Feature", "geometry": {"type": "Point", "coordinates": [-0.461479, -0.000977]}, "properties": {}}, {"type": "Feature", "geometry": {"type": "Point", "coordinates": [-0.454636, -0.000977]}, "properties": {}}, {"type": "Feature", "geometry": {"type": "Point", "coordinates": [-0.457863, -0.000977]}, "properties": {}}, {"type": "Feature", "geometry": {"type": "Point", "coordinates": [-0.458305, -0.000977]}, "properties": {}}, {"type": "Feature", "geometry": {"type": "Point", "coordinates": [-0.401382, -0.000977]}, "properties": {}}, {"type": "Feature", "geometry": {"type": "Point", "coordinates": [-0.338608, -0.030029]}, "properties": {}}, {"type": "Feature", "geometry": {"type": "Point", "coordinates": [-0.48568, -0.030037]}, "properties": {}}, {"type": "Feature", "geometry": {"type": "Point", "coordinates": [-0.42215, -0.030045]}, "properties": {}}, {"type": "Feature", "geometry": {"type": "Point", "coordinates": [-0.453712, -0.030052]}, "properties": {}}, {"type": "Feature", "geometry": {"type": "Point", "coordinates": [-0.374855, -0.03006]}, "properties": {}}, {"type": "Feature", "geometry": {"type": "Point", "coordinates": [-0.458412, -0.000977]}, "properties": {}}, {"type": "Feature", "geometry": {"type": "Point", "coordinates": [-0.404686, -0.000977]}, "properties": {}}, {"type": "Feature", "geometry": {"type": "Point", "coordinates": [-0.351791, -0.000977]}, "properties": {}}, {"type": "Feature", "geometry": {"type": "Point", "coordinates": [-0.314911, -0.000977]}, "properties": {}}, {"type": "Feature", "geometry": {"type": "Point", "coordinates": [-0.256111, -0.000977]}, "properties": {}}, {"type": "Feature", "geometry": {"type": "Point", "coordinates": [-0.193764, -0.000977]}, "properties": {}}, {"type": "Feature", "geometry": {"type": "Point", "coordinates": [-0.177589, -0.000977]}, "properties": {}}, {"type": "Feature", "geometry": {"type": "Point", "coordinates": [-0.223145, -0.000977]}, "properties": {}}, {"type": "Feature", "geometry": {"type": "Point", "coordinates": [-0.306145, -0.000977]}, "properties": {}}, {"type": "Feature", "geometry": {"type": "Point", "coordinates": [-0.381218, -0.000977]}, "properties": {}}, {"type": "Feature", "geometry": {"type": "Point", "coordinates": [-0.413834, -0.029991]}, "properties": {}}, {"type": "Feature", "geometry": {"type": "Point", "coordinates": [-0.226692, -0.029999]}, "properties": {}}, {"type": "Feature", "geometry": {"type": "Point", "coordinates": [-0.236351, -0.030006]}, "properties": {}}, {"type": "Feature", "geometry": {"type": "Point", "coordinates": [-0.290489, -0.030014]}, "properties": {}}, {"type": "Feature", "geometry": {"type": "Point", "coordinates": [-0.319305, -0.030022]}, "properties": {}}, {"type": "Feature", "geometry": {"type": "Point", "coordinates": [0.351013, -0.000977]}, "properties": {}}, {"type": "Feature", "geometry": {"type": "Point", "coordinates": [0.387894, -0.000977]}, "properties": {}}, {"type": "Feature", "geometry": {"type": "Point", "coordinates": [0.457451, -0.000977]}, "properties": {}}, {"type": "Feature", "geometry": {"type": "Point", "coordinates": [0.435524, -0.000977]}, "properties": {}}, {"type": "Feature", "geometry": {"type": "Point", "coordinates": [0.333405, -0.000977]}, "properties": {}}, {"type": "Feature", "geometry": {"type": "Point", "coordinates": [0.288872, -0.000977]}, "properties": {}}, {"type": "Feature", "geometry": {"type": "Point", "coordinates": [0.316841, -0.000977]}, "properties": {}}, {"type": "Feature", "geometry": {"type": "Point", "coordinates": [0.380562, -0.000977]}, "properties": {}}, {"type": "Feature", "geometry": {"type": "Point", "coordinates": [0.457779, -0.000977]}, "properties": {}}, {"type": "Feature", "geometry": {"type": "Point", "coordinates": [0.45153, -0.000977]}, "properties": {}}, {"type": "Feature", "geometry": {"type": "Point", "coordinates": [0.431694, -0.030449]}, "properties": {}}, {"type": "Feature", "geometry": {"type": "Point", "coordinates": [0.361191, -0.030457]}, "properties": {}}, {"type": "Feature", "geometry": {"type": "Point", "coordinates": [0.372208, -0.030464]}, "properties": {}}, {"type": "Feature", "geometry": {"type": "Point", "coordinates": [0.336121, -0.030472]}, "properties": {}}, {"type": "Feature", "geometry": {"type": "Point", "coordinates": [0.447105, -0.030479]}, "properties": {}}, {"type": "Feature", "geometry": {"type": "Point", "coordinates": [-0.041008, -0.000977]}, "properties": {}}, {"type": "Feature", "geometry": {"type": "Point", "coordinates": [-0.030991, -0.000977]}, "properties": {}}, {"type": "Feature", "geometry": {"type": "Point", "coordinates": [-0.103592, -0.000977]}, "properties": {}}, {"type": "Feature", "geometry": {"type": "Point", "coordinates": [-0.118202, -0.000977]}, "properties": {}}, {"type": "Feature", "geometry": {"type": "Point", "coordinates": [-0.144783, -0.000977]}, "properties": {}}, {"type": "Feature", "geometry": {"type": "Point", "coordinates": [-0.118568, -0.000977]}, "properties": {}}, {"type": "Feature", "geometry": {"type": "Point", "coordinates": [-0.14814, -0.000977]}, "properties": {}}, {"type": "Feature", "geometry": {"type": "Point", "coordinates": [-0.126678, -0.000977]}, "properties": {}}, {"type": "Feature", "geometry": {"type": "Point", "coordinates": [-0.080101, -0.000977]}, "properties": {}}, {"type": "Feature", "geometry": {"type": "Point", "coordinates": [-0.042709, -0.000977]}, "properties": {}}, {"type": "Feature", "geometry": {"type": "Point", "coordinates": [-0.050232, -0.030106]}, "properties": {}}, {"type": "Feature", "geometry": {"type": "Point", "coordinates": [-0.077995, -0.030113]}, "properties": {}}, {"type": "Feature", "geometry": {"type": "Point", "coordinates": [-0.054741, -0.030121]}, "properties": {}}, {"type": "Feature", "geometry": {"type": "Point", "coordinates": [-0.054176, -0.030128]}, "properties": {}}, {"type": "Feature", "geometry": {"type": "Point", "coordinates": [-0.066719, -0.030136]}, "properties": {}}, {"type": "Feature", "geometry": {"type": "Point", "coordinates": [0.212364, -0.000977]}, "properties": {}}, {"type": "Feature", "geometry": {"type": "Point", "coordinates": [0.333664, -0.000977]}, "properties": {}}, {"type": "Feature", "geometry": {"type": "Point", "coordinates": [0.335037, -0.000977]}, "properties": {}}, {"type": "Feature", "geometry": {"type": "Point", "coordinates": [0.354645, -0.000977]}, "properties": {}}, {"type": "Feature", "geometry": {"type": "Point", "coordinates": [0.404762, -0.000977]}, "properties": {}}, {"type": "Feature", "geometry": {"type": "Point", "coordinates": [0.470055, -0.000977]}, "properties": {}}, {"type": "Feature", "geometry": {"type": "Point", "coordinates": [0.473335, -0.000977]}, "properties": {}}, {"type": "Feature", "geometry": {"type": "Point", "coordinates": [0.419235, -0.000977]}, "properties": {}}, {"type": "Feature", "geometry": {"type": "Point", "coordinates": [0.371262, -0.000977]}, "properties": {}}, {"type": "Feature", "geometry": {"type": "Point", "coordinates": [0.396385, -0.000977]}, "properties": {}}, {"type": "Feature", "geometry": {"type": "Point", "coordinates": [0.373299, -0.0298]}, "properties": {}}, {"type": "Feature", "geometry": {"type": "Point", "coordinates": [0.492805, -0.029808]}, "properties": {}}, {"type": "Feature", "geometry": {"type": "Point", "coordinates": [0.448547, -0.029816]}, "properties": {}}, {"type": "Feature", "geometry": {"type": "Point", "coordinates": [0.493347, -0.029823]}, "properties": {}}, {"type": "Feature", "geometry": {"type": "Point", "coordinates": [0.398094, -0.029831]}, "properties": {}}, {"type": "Feature", "geometry": {"type": "Point", "coordinates": [-0.326401, -0.000977]}, "properties": {}}, {"type": "Feature", "geometry": {"type": "Point", "coordinates": [-0.400787, -0.000977]}, "properties": {}}, {"type": "Feature", "geometry": {"type": "Point", "coordinates": [-0.46846, -0.000977]}, "properties": {}}, {"type": "Feature", "geometry": {"type": "Point", "coordinates": [-0.453278, -0.000977]}, "properties": {}}, {"type": "Feature", "geometry": {"type": "Point", "coordinates": [-0.390892, -0.000977]}, "properties": {}}, {"type": "Feature", "geometry": {"type": "Point", "coordinates": [-0.325508, -0.000977]}, "properties": {}}, {"type": "Feature", "geometry": {"type": "Point", "coordinates": [-0.328407, -0.000977]}, "properties": {}}, {"type": "Feature", "geometry": {"type": "Point", "coordinates": [-0.389191, -0.000977]}, "properties": {}}, {"type": "Feature", "geometry": {"type": "Point", "coordinates": [-0.407379, -0.000977]}, "properties": {}}, {"type": "Feature", "geometry": {"type": "Point", "coordinates": [-0.464073, -0.000977]}, "properties": {}}, {"type": "Feature", "geometry": {"type": "Point", "coordinates": [-0.4263, -0.030067]}, "properties": {}}, {"type": "Feature", "geometry": {"type": "Point", "coordinates": [-0.414383, -0.030075]}, "properties": {}}, {"type": "Feature", "geometry": {"type": "Point", "coordinates": [-0.448692, -0.030083]}, "properties": {}}, {"type": "Feature", "geometry": {"type": "Point", "coordinates": [-0.485146, -0.03009]}, "properties": {}}, {"type": "Feature", "geometry": {"type": "Point", "coordinates": [-0.376198, -0.030098]}, "properties": {}}, {"type": "Feature", "geometry": {"type": "Point", "coordinates": [0.127121, -0.000977]}, "properties": {}}, {"type": "Feature", "geometry": {"type": "Point", "coordinates": [0.167618, -0.000977]}, "properties": {}}, {"type": "Feature", "geometry": {"type": "Point", "coordinates": [0.195145, -0.000977]}, "properties": {}}, {"type": "Feature", "geometry": {"type": "Point", "coordinates": [0.246246, -0.000977]}, "properties": {}}, {"type": "Feature", "geometry": {"type": "Point", "coordinates": [0.266823, -0.000977]}, "properties": {}}, {"type": "Feature", "geometry": {"type": "Point", "coordinates": [0.222588, -0.000977]}, "properties": {}}, {"type": "Feature", "geometry": {"type": "Point", "coordinates": [0.255363, -0.000977]}, "properties": {}}, {"type": "Feature", "geometry": {"type": "Point", "coordinates": [0.217659, -0.000977]}, "properties": {}}, {"type": "Feature", "geometry": {"type": "Point", "coordinates": [0.128036, -0.000977]}, "properties": {}}, {"type": "Feature", "geometry": {"type": "Point", "coordinates": [0.187004, -0.000977]}, "properties": {}}, {"type": "Feature", "geometry": {"type": "Point", "coordinates": [0.270782, -0.030296]}, "properties": {}}, {"type": "Feature", "geometry": {"type": "Point", "coordinates": [0.140541, -0.030304]}, "properties": {}}, {"type": "Feature", "geometry": {"type": "Point", "coordinates": [0.147003, -0.030312]}, "properties": {}}, {"type": "Feature", "geometry": {"type": "Point", "coordinates": [0.162422, -0.030319]}, "properties": {}}, {"type": "Feature", "geometry": {"type": "Point", "coordinates": [0.269875, -0.030327]}, "properties": {}}, {"type": "Feature", "geometry": {"type": "Point", "coordinates": [0.053215, -0.000977]}, "properties": {}}, {"type": "Feature", "geometry": {"type": "Point", "coordinates": [0.006638, -0.000977]}, "properties": {}}, {"type": "Feature", "geometry": {"type": "Point", "coordinates": [-0.054039, -0.000977]}, "properties": {}}, {"type": "Feature", "geometry": {"type": "Point", "coordinates": [-0.067322, -0.000977]}, "properties": {}}, {"type": "Feature", "geometry": {"type": "Point", "coordinates": [-0.065063, -0.000977]}, "properties": {}}, {"type": "Feature", "geometry": {"type": "Point", "coordinates": [-0.072716, -0.000977]}, "properties": {}}, {"type": "Feature", "geometry": {"type": "Point", "coordinates": [-0.012894, -0.000977]}, "properties": {}}, {"type": "Feature", "geometry": {"type": "Point", "coordinates": [0.047722, -0.000977]}, "properties": {}}, {"type": "Feature", "geometry": {"type": "Point", "coordinates": [0.066811, -0.000977]}, "properties": {}}, {"type": "Feature", "geometry": {"type": "Point", "coordinates": [0.026543, -0.000977]}, "properties": {}}, {"type": "Feature", "geometry": {"type": "Point", "coordinates": [0.033333, -0.029877]}, "properties": {}}, {"type": "Feature", "geometry": {"type": "Point", "coordinates": [-0.011032, -0.029884]}, "properties": {}}, {"type": "Feature", "geometry": {"type": "Point", "coordinates": [-0.003418, -0.029892]}, "properties": {}}, {"type": "Feature", "geometry": {"type": "Point", "coordinates": [-0.046692, -0.0299]}, "properties": {}}, {"type": "Feature", "geometry": {"type": "Point", "coordinates": [-0.014267, -0.029907]}, "properties": {}}, {"type": "Feature", "geometry": {"type": "Point", "coordinates": [0.267624, -0.000977]}, "properties": {}}, {"type": "Feature", "geometry": {"type": "Point", "coordinates": [-0.300117, -0.000977]}, "properties": {}}, {"type": "Feature", "geometry": {"type": "Point", "coordinates": [0.281265, -0.000977]}, "properties": {}}, {"type": "Feature", "geometry": {"type": "Point", "coordinates": [0.246353, -0.000977]}, "properties": {}}, {"type": "Feature", "geometry": {"type": "Point", "coordinates": [0.216408, -0.000977]}, "properties": {}}, {"type": "Feature", "geometry": {"type": "Point", "coordinates": [0.15699, -0.000977]}, "properties": {}}, {"type": "Feature", "geometry": {"type": "Point", "coordinates": [0.201843, -0.000977]}, "properties": {}}, {"type": "Feature", "geometry": {"type": "Point", "coordinates": [0.202232, -0.000977]}, "properties": {}}, {"type": "Feature", "geometry": {"type": "Point", "coordinates": [0.163422, -0.000977]}, "properties": {}}, {"type": "Feature", "geometry": {"type": "Point", "coordinates": [0.144875, -0.000977]}, "properties": {}}, {"type": "Feature", "geometry": {"type": "Point", "coordinates": [0.124756, -0.030334]}, "properties": {}}, {"type": "Feature", "geometry": {"type": "Point", "coordinates": [0.245346, -0.030342]}, "properties": {}}, {"type": "Feature", "geometry": {"type": "Point", "coordinates": [0.253525, -0.03035]}, "properties": {}}, {"type": "Feature", "geometry": {"type": "Point", "coordinates": [0.284149, -0.030357]}, "properties": {}}, {"type": "Feature", "geometry": {"type": "Point", "coordinates": [0.313293, -0.030365]}, "properties": {}}, {"type": "Feature", "geometry": {"type": "Point", "coordinates": [-0.187973, -0.000977]}, "properties": {}}, {"type": "Feature", "geometry": {"type": "Point", "coordinates": [-0.174622, -0.000977]}, "properties": {}}, {"type": "Feature", "geometry": {"type": "Point", "coordinates": [-0.194084, -0.000977]}, "properties": {}}, {"type": "Feature", "geometry": {"type": "Point", "coordinates": [-0.260048, -0.000977]}, "properties": {}}, {"type": "Feature", "geometry": {"type": "Point", "coordinates": [-0.279625, -0.000977]}, "properties": {}}, {"type": "Feature", "geometry": {"type": "Point", "coordinates": [-0.254189, -0.000977]}, "properties": {}}, {"type": "Feature", "geometry": {"type": "Point", "coordinates": [-0.268929, -0.000977]}, "properties": {}}, {"type": "Feature", "geometry": {"type": "Point", "coordinates": [-0.237495, -0.000977]}, "properties": {}}, {"type": "Feature", "geometry": {"type": "Point", "coordinates": [-0.197212, -0.000977]}, "properties": {}}, {"type": "Feature", "geometry": {"type": "Point", "coordinates": [-0.21566, -0.000977]}, "properties": {}}, {"type": "Feature", "geometry": {"type": "Point", "coordinates": [-0.244705, -0.030144]}, "properties": {}}, {"type": "Feature", "geometry": {"type": "Point", "coordinates": [-0.212769, -0.030151]}, "properties": {}}, {"type": "Feature", "geometry": {"type": "Point", "coordinates": [-0.21656, -0.030159]}, "properties": {}}, {"type": "Feature", "geometry": {"type": "Point", "coordinates": [-0.229897, -0.030167]}, "properties": {}}, {"type": "Feature", "geometry": {"type": "Point", "coordinates": [-0.243851, -0.030174]}, "properties": {}}, {"type": "Feature", "geometry": {"type": "Point", "coordinates": [0.081772, -0.000977]}, "properties": {}}, {"type": "Feature", "geometry": {"type": "Point", "coordinates": [0.046837, -0.000977]}, "properties": {}}, {"type": "Feature", "geometry": {"type": "Point", "coordinates": [0.01503, -0.000977]}, "properties": {}}, {"type": "Feature", "geometry": {"type": "Point", "coordinates": [0.007492, -0.000977]}, "properties": {}}, {"type": "Feature", "geometry": {"type": "Point", "coordinates": [0.095642, -0.000977]}, "properties": {}}, {"type": "Feature", "geometry": {"type": "Point", "coordinates": [0.090271, -0.000977]}, "properties": {}}, {"type": "Feature", "geometry": {"type": "Point", "coordinates": [0.037514, -0.000977]}, "properties": {}}, {"type": "Feature", "geometry": {"type": "Point", "coordinates": [0.076317, -0.000977]}, "properties": {}}, {"type": "Feature", "geometry": {"type": "Point", "coordinates": [0.037201, -0.000977]}, "properties": {}}, {"type": "Feature", "geometry": {"type": "Point", "coordinates": [0.018921, -0.000977]}, "properties": {}}, {"type": "Feature", "geometry": {"type": "Point", "coordinates": [0.009804, -0.030182]}, "properties": {}}, {"type": "Feature", "geometry": {"type": "Point", "coordinates": [0.038193, -0.03019]}, "properties": {}}, {"type": "Feature", "geometry": {"type": "Point", "coordinates": [0.000763, -0.030197]}, "properties": {}}, {"type": "Feature", "geometry": {"type": "Point", "coordinates": [0.05864, -0.030205]}, "properties": {}}, {"type": "Feature", "geometry": {"type": "Point", "coordinates": [0.020149, -0.030212]}, "properties": {}}]}